jupyterlab_nodeeditor/__init__.py
jupyterlab_nodeeditor/_version.py
jupyterlab_nodeeditor/select.py
jupyterlab_nodeeditor/slider.py
jupyterlab_nodeeditor/utils.py
jupyterlab_nodeeditor-1.0.10.data/data/share/jupyter/labextensions/jupyterlab_nodeeditor/package.json
jupyterlab_nodeeditor-1.0.10.data/data/share/jupyter/labextensions/jupyterlab_nodeeditor/schemas/jupyterlab_nodeeditor/package.json.orig
jupyterlab_nodeeditor-1.0.10.data/data/share/jupyter/labextensions/jupyterlab_nodeeditor/schemas/jupyterlab_nodeeditor/plugin.json
jupyterlab_nodeeditor-1.0.10.data/data/share/jupyter/labextensions/jupyterlab_nodeeditor/static/1065.9fc232a423740f88d7f7.js
jupyterlab_nodeeditor-1.0.10.data/data/share/jupyter/labextensions/jupyterlab_nodeeditor/static/1065.9fc232a423740f88d7f7.js.LICENSE.txt
jupyterlab_nodeeditor-1.0.10.data/data/share/jupyter/labextensions/jupyterlab_nodeeditor/static/1134.0798a6e0f0b366f5ec0e.js
jupyterlab_nodeeditor-1.0.10.data/data/share/jupyter/labextensions/jupyterlab_nodeeditor/static/1134.0798a6e0f0b366f5ec0e.js.LICENSE.txt
jupyterlab_nodeeditor-1.0.10.data/data/share/jupyter/labextensions/jupyterlab_nodeeditor/static/1147.39b1dbd1dc9f44484129.js
jupyterlab_nodeeditor-1.0.10.data/data/share/jupyter/labextensions/jupyterlab_nodeeditor/static/1147.39b1dbd1dc9f44484129.js.LICENSE.txt
jupyterlab_nodeeditor-1.0.10.data/data/share/jupyter/labextensions/jupyterlab_nodeeditor/static/1156.51b1cd7d3c43a2460f5b.js
jupyterlab_nodeeditor-1.0.10.data/data/share/jupyter/labextensions/jupyterlab_nodeeditor/static/1156.51b1cd7d3c43a2460f5b.js.LICENSE.txt
jupyterlab_nodeeditor-1.0.10.data/data/share/jupyter/labextensions/jupyterlab_nodeeditor/static/1259.c5ce71099876a9077b0e.js
jupyterlab_nodeeditor-1.0.10.data/data/share/jupyter/labextensions/jupyterlab_nodeeditor/static/1259.c5ce71099876a9077b0e.js.LICENSE.txt
jupyterlab_nodeeditor-1.0.10.data/data/share/jupyter/labextensions/jupyterlab_nodeeditor/static/1448.4cd0d08640480a20e1be.js
jupyterlab_nodeeditor-1.0.10.dist-info/METADATA
jupyterlab_nodeeditor-1.0.10.dist-info/WHEEL
jupyterlab_nodeeditor-1.0.10.dist-info/licenses/LICENSE
jupyterlab_nodeeditor-1.0.10.dist-info/RECORD
