Metadata-Version: 2.1
Name: jupyterlab_nodeeditor
Version: 1.0.10
Summary: 一个节点编辑器
Project-URL: Homepage, https://github.com/github_username/jupyterlab_nodeeditor
Project-URL: Bug Tracker, https://github.com/github_username/jupyterlab_nodeeditor/issues
Project-URL: Repository, https://github.com/github_username/jupyterlab_nodeeditor.git
Author-email: l0n0l <cenlan@hotmail.com>
License: BSD 3-Clause License
License-File: LICENSE
Classifier: Framework :: Jupyter
Classifier: Framework :: Jupyter :: JupyterLab
Classifier: Framework :: Jupyter :: JupyterLab :: 4
Classifier: Framework :: Jupyter :: JupyterLab :: Extensions
Classifier: Framework :: Jupyter :: JupyterLab :: Extensions :: Prebuilt
Classifier: License :: OSI Approved :: BSD License
Classifier: Programming Language :: Python
Classifier: Programming Language :: Python :: 3
Classifier: Programming Language :: Python :: 3.8
Classifier: Programming Language :: Python :: 3.9
Classifier: Programming Language :: Python :: 3.10
Classifier: Programming Language :: Python :: 3.11
Requires-Python: >=3.8
Requires-Dist: svg-path
